{
  "Triggers": [
    {
      "Name": "Rare Discovery",
      "Pattern": "Dullah has discovered",
      "Enabled": false,
      "CaseSensitive": false,
      "SoundFile": "Sounds/Alert.wav"
    },
    {
      "Name": "Darsh",
      "Pattern": "\u0022darsh \u0022",
      "Enabled": false,
      "CaseSensitive": false,
      "SoundFile": "Sounds/Alert5.wav"
    },
    {
      "Name": "Books",
      "Pattern": "books",
      "Enabled": false,
      "CaseSensitive": false,
      "SoundFile": "Sounds/Alert5.wav"
    },
    {
      "Name": "Curator",
      "Pattern": "has struck down the Curator",
      "Enabled": false,
      "CaseSensitive": false,
      "SoundFile": "Sounds/Alert5.wav"
    },
    {
      "Name": "Death",
      "Pattern": "Your corpse is located at",
      "Enabled": false,
      "CaseSensitive": false,
      "SoundFile": "Sounds/Alert2.wav"
    },
    {
      "Name": "Event",
      "Pattern": "event at",
      "Enabled": false,
      "CaseSensitive": false,
      "SoundFile": "Sounds/Alert5.wav"
    },
    {
      "Name": "Tells",
      "Pattern": "tells you,",
      "Enabled": false,
      "CaseSensitive": false,
      "SoundFile": "Sounds/chimesoft.wav"
    },
    {
      "Name": "Death2",
      "Pattern": "You do not need to recover your corpse!",
      "Enabled": false,
      "CaseSensitive": false,
      "SoundFile": "Sounds/notify2.wav"
    }
  ]
}